{
  "version": "mrrakc/v0",
  "kind": "history/gate",
  "metadata": {
    "tags": []
  },
  "spec": {
    "name": "Bab Dar Sinaâ",
    "id": "bab-dar-sina",
    "description": "No description available.",
    "location": {
      "longitude": 34.0332923,
      "latitude": -6.8216139,
      "province": "province/sale"
    },
    "people": [],
    "timeline": [],
    "links": [],
    "activities": [],
    "items": [],
    "access": {
      "type": "public",
      "status": "open",
      "options": []
    },
    "timePeriods": [],
    "comments": []
  }
}