{
  "version": "mrrakc/v0",
  "kind": "urban/park",
  "metadata": {
    "tags": []
  },
  "spec": {
    "name": "Freedom Park",
    "id": "freedom-park",
    "description": "No description available.",
    "location": {
      "longitude": 34.0340659,
      "latitude": -6.7783176,
      "province": "province/sale"
    },
    "people": [],
    "timeline": [],
    "links": [],
    "activities": [],
    "items": [],
    "access": {
      "type": "public",
      "status": "open",
      "options": []
    },
    "timePeriods": [],
    "comments": []
  }
}