{
  "version": "mrrakc/v0",
  "kind": "architecture/hotel",
  "metadata": {
    "tags": []
  },
  "spec": {
    "name": "Hotel Particulier 2",
    "id": "hotel-particulier-2",
    "description": "No description available",
    "location": {
      "longitude": 33.5901432,
      "latitude": -7.6249155,
      "province": "province/casablanca"
    },
    "people": [
      {
        "id": "people/emmanuel-chaine",
        "relationship": [
          "Architect"
        ]
      }
    ],
    "timeline": [
      {
        "title": "Construction",
        "date": "1931",
        "description": "Built in 1930/1931"
      }
    ],
    "links": [],
    "activities": [],
    "items": [],
    "access": {
      "type": "public",
      "options": [
        {
          "title": "Exterior viewing",
          "modality": "free",
          "audience": "all",
          "entranceFee": 0
        }
      ],
      "status": "open"
    },
    "timePeriods": [
      "20th Century"
    ]
  }
}
