{
  "version": "mrrakc/v0",
  "kind": "culture/museum",
  "metadata": {
    "tags": []
  },
  "spec": {
    "name": "Najoua El Hitmi Zawia Factory",
    "id": "najoua-el-hitmi-zawia-factory",
    "description": "No description available.",
    "location": {
      "longitude": 35.7810499,
      "latitude": -5.809498,
      "province": "province/tangier-assilah"
    },
    "people": [],
    "timeline": [],
    "links": [],
    "activities": [],
    "items": [],
    "access": {
      "type": "public",
      "status": "open",
      "options": []
    },
    "timePeriods": [],
    "comments": []
  }
}