{
  "version": "mrrakc/v0",
  "kind": "nature/lake",
  "metadata": {
    "tags": []
  },
  "spec": {
    "name": "Hachlaf Lake",
    "id": "hachlaf-lake",
    "description": "No description available.",
    "location": {
      "longitude": 33.5511777,
      "latitude": -4.9993958,
      "province": "province/ifrane"
    },
    "people": [],
    "timeline": [],
    "links": [],
    "activities": [],
    "items": [],
    "access": {
      "type": "public",
      "status": "open",
      "options": []
    },
    "timePeriods": [],
    "comments": []
  }
}