{
  "kind": "history/gate",
  "spec": {
    "name": "Bab Nqob",
    "id": "bab-nqob",
    "description": "No description available",
    "location": {
      "province": "province/marrakesh",
      "longitude": -8.000813,
      "latitude": 31.62822,
      "altitude": 0.0
    },
    "access": {
      "type": "public",
      "status": "open",
      "options": []
    },
    "timePeriods": [],
    "people": [],
    "timeline": [],
    "links": [],
    "activities": [],
    "items": [],
    "comments": []
  }
}