{
  "version": "mrrakc/v0",
  "kind": "nature/mountain",
  "metadata": {
    "tags": [
      "Imlil",
      "Central High Atlas"
    ]
  },
  "spec": {
    "name": "Mount Agouti",
    "id": "mount-agouti",
    "description": "No description available",
    "location": {
      "longitude": -6.5167,
      "latitude": 31.5456,
      "altitude": 3500,
      "province": "province/azilal"
    },
    "people": [],
    "timeline": [],
    "links": [],
    "activities": [],
    "items": [],
    "access": {
      "type": "public",
      "status": "open",
      "options": []
    },
    "timePeriods": [],
    "comments": []
  }
}
