{
  "version": "mrrakc/v0",
  "kind": "nature/mountain",
  "metadata": {
    "tags": []
  },
  "spec": {
    "name": "Mount Awltoum",
    "id": "mount-awltoum",
    "description": "Mountain Chain: Central High Atlas",
    "location": {
      "longitude": -6.6775916,
      "latitude": 31.5582053,
      "altitude": 3121,
      "province": "province/azilal"
    },
    "people": [],
    "timeline": [],
    "links": [],
    "activities": [],
    "items": [],
    "access": {
      "type": "public",
      "status": "open",
      "options": []
    },
    "timePeriods": [],
    "comments": []
  }
}
