{
  "version": "mrrakc/v0",
  "kind": "urban/square",
  "metadata": {
    "tags": []
  },
  "spec": {
    "name": "Michouar's square",
    "id": "michouars-square",
    "description": "No description available.",
    "location": {
      "longitude": -5.3690509,
      "latitude": 35.5703629,
      "province": "province/tetouan"
    },
    "people": [],
    "timeline": [],
    "links": [],
    "activities": [],
    "items": [],
    "access": {
      "type": "public",
      "status": "open",
      "options": []
    },
    "timePeriods": [],
    "comments": []
  }
}
