{
  "version": "mrrakc/v0",
  "kind": "religion/mausoleum",
  "metadata": {
    "tags": []
  },
  "spec": {
    "name": "Sidi el Mendri Mausoleum",
    "id": "sidi-el-mendri-mausoleum",
    "description": "No description available.",
    "location": {
      "longitude": 35.5740074,
      "latitude": -5.3680577,
      "province": "province/tetouan"
    },
    "people": [],
    "timeline": [],
    "links": [],
    "activities": [],
    "items": [],
    "access": {
      "type": "public",
      "status": "open",
      "options": []
    },
    "timePeriods": [],
    "comments": []
  }
}