{
  "version": "mrrakc/v0",
  "kind": "shopping/market",
  "metadata": {
    "tags": []
  },
  "spec": {
    "name": "Covered Market of Ain Chock",
    "slug": "covered-market-of-ain-chock",
    "description": "",
    "location": {
      "administrativeArea": "province/casablanca",
      "longitude": 33.5521697,
      "latitude": -7.5993081
    },
    "people": [],
    "timeline": [],
    "links": [],
    "activities": [],
    "items": [],
    "access": {
      "type": "public",
      "options": []
    },
    "timePeriod": ""
  }
}