{
  "version": "mrrakc/v0",
  "kind": "food/restaurant",
  "metadata": {
    "tags": []
  },
  "spec": {
    "name": "Dar Dada Restaurant",
    "slug": "dar-dada-restaurant",
    "description": "🔻 Menu: Moroccan<br>🔻 Tags: Fine Dining",
    "location": {
      "longitude": 33.6039639,
      "latitude": -7.6213916,
      "province": "province/casablanca"
    },
    "people": [],
    "timeline": [],
    "links": [],
    "activities": [],
    "items": [],
    "access": {
      "type": "public",
      "options": []
    },
    "timePeriod": ""
  }
}