{
  "version": "mrrakc/v0",
  "kind": "urban/park",
  "metadata": {
    "tags": []
  },
  "spec": {
    "name": "l'Hermitage Garden",
    "id": "l-hermitage-garden",
    "description": "None",
    "location": {
      "longitude": 33.5644556,
      "latitude": -7.6132002,
      "province": "province/casablanca"
    },
    "people": [],
    "timeline": [],
    "links": [],
    "activities": [],
    "items": [],
    "access": {
      "type": "public",
      "options": [],
      "status": "open"
    },
    "timePeriods": [
      ""
    ]
  }
}