{
  "version": "mrrakc/v0",
  "kind": "architecture/palace ",
  "metadata": {
    "tags": []
  },
  "spec": {
    "name": "Royal Palace",
    "slug": "royal-palace",
    "description": "",
    "location": {
      "administrativeArea": "province/casablanca",
      "longitude": 33.5803387,
      "latitude": -7.6054573
    },
    "people": [],
    "timeline": [],
    "links": [],
    "activities": [],
    "items": [],
    "access": {
      "type": "public",
      "options": []
    },
    "timePeriod": ""
  }
}