{
  "version": "mrrakc/v0",
  "kind": "nature/dam",
  "metadata": {
    "tags": []
  },
  "spec": {
    "name": "Bou Ghaliya Beni Zrantel Dam",
    "id": "bou-ghaliya-beni-zrantel-dam",
    "description": "No description available.",
    "location": {
      "longitude": -6.1459595,
      "latitude": 32.7477413,
      "province": "province/khouribga"
    },
    "people": [],
    "timeline": [],
    "links": [],
    "activities": [],
    "items": [],
    "access": {
      "type": "public",
      "status": "open",
      "options": []
    },
    "timePeriods": [],
    "comments": []
  }
}
