{
  "version": "mrrakc/v0",
  "kind": "nature/mountain",
  "metadata": {
    "tags": [
      "Taza",
      "Middle Atlas"
    ]
  },
  "spec": {
    "name": "Mount Bou Iblane",
    "id": "mount-bou-iblane",
    "description": "No description available",
    "location": {
      "longitude": 33.6779256,
      "latitude": -4.0738678,
      "altitude": 3082,
      "province": "province/guercif"
    },
    "people": [],
    "timeline": [],
    "links": [],
    "activities": [],
    "items": [],
    "access": {
      "type": "public",
      "status": "open",
      "options": []
    },
    "timePeriods": [],
    "comments": []
  }
}