{
  "version": "mrrakc/v0",
  "kind": "nature/lake",
  "metadata": {
    "tags": []
  },
  "spec": {
    "name": "Moulay Yaakoub Lake",
    "id": "moulay-yaakoub-lake",
    "description": "No description available.",
    "location": {
      "longitude": -5.5840465,
      "latitude": 32.6126365,
      "province": "province/khenifra"
    },
    "people": [],
    "timeline": [],
    "links": [],
    "activities": [],
    "items": [],
    "access": {
      "type": "public",
      "status": "open",
      "options": []
    },
    "timePeriods": [],
    "comments": []
  }
}
